qcrepocleaner/Ccdb.py
qcrepocleaner/__init__.py
qcrepocleaner/binUtils.py
qcrepocleaner/o2-qc-repo-cleaner
qcrepocleaner/o2-qc-repo-delete-not-in-runs
qcrepocleaner/o2-qc-repo-delete-objects
qcrepocleaner/o2-qc-repo-delete-objects-in-runs
qcrepocleaner/o2-qc-repo-delete-time-interval
qcrepocleaner/o2-qc-repo-find-objects-not-updated
qcrepocleaner/o2-qc-repo-move-objects
qcrepocleaner/o2-qc-repo-update-run-type
qcrepocleaner/pidfile.py
qcrepocleaner/policies_utils.py
qcrepocleaner/rules/1_per_hour.py
qcrepocleaner/rules/1_per_run.py
qcrepocleaner/rules/__init__.py
qcrepocleaner/rules/last_only.py
qcrepocleaner/rules/multiple_per_run.py
qcrepocleaner/rules/none_kept.py
qcrepocleaner/rules/plugin_template.py
qcrepocleaner/rules/production.py
qcrepocleaner/rules/skip.py
qcrepocleaner-1.10.data/scripts/o2-qc-repo-cleaner
qcrepocleaner-1.10.data/scripts/o2-qc-repo-delete-not-in-runs
qcrepocleaner-1.10.data/scripts/o2-qc-repo-delete-objects
qcrepocleaner-1.10.data/scripts/o2-qc-repo-delete-objects-in-runs
qcrepocleaner-1.10.data/scripts/o2-qc-repo-delete-time-interval
qcrepocleaner-1.10.data/scripts/o2-qc-repo-find-objects-not-updated
qcrepocleaner-1.10.data/scripts/o2-qc-repo-move-objects
qcrepocleaner-1.10.data/scripts/o2-qc-repo-update-run-type
tests/__init__.py
tests/test_1_per_hour.py
tests/test_1_per_run.py
tests/test_Ccdb.py
tests/test_MultiplePerRun.py
tests/test_MultiplePerRun_deleteFirstLast.py
tests/test_Production.py
tests/test_last_only.py
tests/test_repoCleaner.py
tests/test_utils.py
qcrepocleaner-1.10.dist-info/METADATA
qcrepocleaner-1.10.dist-info/WHEEL
qcrepocleaner-1.10.dist-info/top_level.txt
qcrepocleaner-1.10.dist-info/RECORD
