Metadata-Version: 2.1
Name: qcrepocleaner
Version: 1.10
Summary: Set of tools to clean up the QCDB repository.
Home-page: https://gitlab.cern.ch/AliceO2Group/QualityControl/Framework/script/RepoCleaner
Author: Barthelemy von Haller
Author-email: bvonhall@cern.ch
License: GPLv3
Classifier: License :: OSI Approved :: GNU General Public License v3 (GPLv3)
Classifier: Programming Language :: Python :: 3
Classifier: Topic :: Utilities
Classifier: Environment :: Console
Classifier: Operating System :: Unix
Classifier: Development Status :: 5 - Production/Stable
Requires-Python: >=3.6
Requires-Dist: requests
Requires-Dist: dryable
Requires-Dist: responses
Requires-Dist: PyYAML
Requires-Dist: python-consul
Requires-Dist: psutil
